drf_simple_api_errors/__init__.py
drf_simple_api_errors/apps.py
drf_simple_api_errors/exception_handler.py
drf_simple_api_errors/extra_handlers.py
drf_simple_api_errors/formatter.py
drf_simple_api_errors/handlers.py
drf_simple_api_errors/settings.py
drf_simple_api_errors/types.py
drf_simple_api_errors/utils.py
drf_simple_api_errors-2.1.1.dist-info/METADATA
drf_simple_api_errors-2.1.1.dist-info/WHEEL
drf_simple_api_errors-2.1.1.dist-info/licenses/LICENSE.md
drf_simple_api_errors-2.1.1.dist-info/RECORD
