Metadata-Version: 2.4
Name: drf-simple-api-errors
Version: 2.1.1
Summary: A library for Django Rest Framework returning consistent and easy-to-parse API error messages.
License: MIT
License-File: LICENSE.md
Keywords: python,django,django rest framework,drf,error handling,errors,exceptions
Author: Gian
Author-email: 30044863+gripep@users.noreply.github.com
Requires-Python: >=3.9,<4.0
Classifier: Framework :: Django
Classifier: License :: OSI Approved :: MIT License
Classifier: Operating System :: OS Independent
Classifier: Programming Language :: Python
Classifier: Programming Language :: Python :: 3
Classifier: Programming Language :: Python :: 3.9
Classifier: Programming Language :: Python :: 3.10
Classifier: Programming Language :: Python :: 3.11
Classifier: Programming Language :: Python :: 3.12
Classifier: Programming Language :: Python :: 3.13
Classifier: Programming Language :: Python :: 3.14
Classifier: Topic :: Software Development :: Libraries :: Application Frameworks
Classifier: Topic :: Software Development :: Libraries :: Python Modules
Requires-Dist: Django (>=2.2)
Requires-Dist: djangorestframework (>=3.0)
Project-URL: Documentation, https://github.com/gripep/drf-simple-api-errors/blob/master/README.md
Project-URL: Homepage, https://github.com/gripep/drf-simple-api-errors
Project-URL: Repository, https://github.com/gripep/drf-simple-api-errors
